{
  "stakePool": {
    "pubkey": "Zdw34cuhqTAmkrMuFum6CCrx8fQNqNevAZMD4vVipmM",
    "data": "{\"type\":\"Buffer\",\"data\":[121,34,206,21,79,127,255,28,252,11,107,150,129,217,223,103,113,46,51,100,253,169,184,220,169,233,187,174,114,149,80,234,149,99,56,125,224,19,33,209,152,16,0,0,0,0,1,10,0,0,0,1,10,0,0,0,0,6,144,128,201,64,134,91,102,18,81,59,174,245,164,232,141,122,52,44,92,214,252,183,214,104,220,71,239,168,141,50,77,6,144,128,201,64,134,91,102,18,81,59,174,245,164,232,141,122,52,44,92,214,252,183,214,104,220,71,239,168,141,50,77,0,0,0,0,0,1,0,0,0,232,152,65,124,86,186,91,168,249,178,215,21,193,56,125,180,11,174,48,172,173,14,251,168,66,201,192,77,85,101,136,244,29,0,0,0,112,111,111,108,45,110,97,109,101,45,48,46,49,55,54,54,48,50,56,56,55,57,50,57,55,49,55,50,51]}",
    "executable": false,
    "lamports": 2248080,
    "owner": "crcBwD7wUjzwsy8tJsVCzZvBTHeq5GoboGg84YraRyd",
    "rentEpoch": 0,
    "type": "stakePool",
    "parsed": {
      "bump": "252",
      "authority": "madtRbRV8Dso6V3annY8Y5R7HAFQTbhUTRANuuP4DYB",
      "totalStaked": "16",
      "resetOnUnstake": "false",
      "cooldownSeconds": "10",
      "minStakeSeconds": "10",
      "stakePaymentInfo": "SdFEeJxn7XxcnYEMNpnoMMSsTfmA1bHfiRdu6qra7zL",
      "unstakePaymentInfo": "SdFEeJxn7XxcnYEMNpnoMMSsTfmA1bHfiRdu6qra7zL",
      "requiresAuthorization": "false",
      "allowedCreators": "",
      "allowedCollections": "GexF22fC8rmyNXBUFjitu8ydHeZ8Srmy2iJWLJSQkLyH",
      "identifier": "pool-name-0.17660288792971723"
    }
  },
  "rewardDistributor": {
    "timestamp": 1693179556696,
    "pubkey": "C9SCyVUfoNJnYQDWgWN8CHQErjo7oNeRZk4kePJR7Cak",
    "data": "{\"type\":\"Buffer\",\"data\":[215,10,217,199,104,194,97,227,253,8,92,88,58,40,149,83,181,251,111,68,223,238,193,232,13,201,204,93,228,86,94,2,250,71,43,136,179,216,246,204,176,0,11,107,150,129,217,223,103,113,46,51,100,253,169,184,220,169,233,187,174,114,149,80,234,149,99,56,125,224,19,33,209,152,0,0,0,0,0,0,0,0,226,184,92,194,166,65,150,78,0,31,212,214,6,9,119,220,73,34,233,83,50,144,89,136,34,104,46,35,93,108,116,115,64,120,125,1,0,0,0,0,10,0,0,0,0,0,0,0,0,0,0,0,0,0,0,0,0,192,175,214,145,54,0,0,0,0,0,0,0,0,0,0,1,0,0,0,0,0,0,0,0,6,144,128,201,64,134,91,102,18,81,59,174,245,164,232,141,122,52,44,92,214,252,183,214,104,220,71,239,168,141,50,77,0,0,0,0,0,0,0,0,0,0,0,0,0,0,0,0,0,0,0,0,0,0,0,0,0,0,0,0,0,0,0,0,0,0,0,0,0,0,0,0,0,0,0,0,0,0,0,0,0,0,0,0,0,0,0,0,0,0,0,0,0,0,0,0,0,0,0,0,0,0,0,0,0,0,0,0,0,0,0,0,0,0,0,0,0,0,0,0,0,0,0,0,0]}",
    "executable": false,
    "lamports": 2895360,
    "owner": "crcBwD7wUjzwsy8tJsVCzZvBTHeq5GoboGg84YraRyd",
    "rentEpoch": 0,
    "type": "rewardDistributor",
    "parsed": {
      "bump": "253",
      "stakePool": "Zdw34cuhqTAmkrMuFum6CCrx8fQNqNevAZMD4vVipmM",
      "kind": "0",
      "authority": "madtRbRV8Dso6V3annY8Y5R7HAFQTbhUTRANuuP4DYB",
      "identifier": "0",
      "rewardMint": "GG2C4UFshHa457EwdEoa32XZH7cQ6bSMWWxRw4BjCr1x",
      "rewardAmount": "25000000",
      "rewardDurationSeconds": "10",
      "rewardsIssued": "60000000000000",
      "defaultMultiplier": "1",
      "multiplierDecimals": "0",
      "claimRewardsPaymentInfo": "SdFEeJxn7XxcnYEMNpnoMMSsTfmA1bHfiRdu6qra7zL"
    }
  },
  "rewardDistributorTokenAccount": {
    "address": "2sjctLEyBramEYuxYwwVFtbeQxh8ghhRMwv8qS1mv8Y9",
    "mint": "GG2C4UFshHa457EwdEoa32XZH7cQ6bSMWWxRw4BjCr1x",
    "owner": "C9SCyVUfoNJnYQDWgWN8CHQErjo7oNeRZk4kePJR7Cak",
    "amount": "0",
    "delegate": null,
    "delegatedAmount": "0",
    "isInitialized": true,
    "isFrozen": false,
    "isNative": false,
    "closeAuthority": null,
    "tlvData": {
      "type": "Buffer",
      "data": "[]"
    }
  },
  "stakeEntries": [
    {
      "pubkey": "EbzgaMmCoNRV2brmvsBmqJbGHeHjTz9JGhKKinb4oifu",
      "data": "{\"type\":\"Buffer\",\"data\":[187,127,9,35,155,68,86,40,254,0,8,92,88,58,40,149,83,181,251,111,68,223,238,193,232,13,201,204,93,228,86,94,2,250,71,43,136,179,216,246,204,176,0,0,0,0,0,0,0,0,131,181,220,33,105,202,99,28,41,177,96,142,83,145,164,104,223,252,30,70,215,94,98,35,166,233,113,142,159,168,91,140,0,0,0,0,0,0,0,0,0,0,0,0,0,0,0,0,0,0,0,0,0,0,0,0,0,0,0,0,0,0,0,0,182,102,37,100,0,0,0,0,147,134,205,100,0,0,0,0,122,134,158,0,0,0,0,0,0,0,0,0,0,0,0,0,0,0,0,0,0,0,0,0,0,0,0,0,0,0,0,0,0,0,0,0,0,0,0,0,0,0,0,0,0,0,0,0,0,0,0,0,0,0,0,0,0,0,0,0,0,0,0,0,0,0,0,0,0,0,0,0,0,0,0,0,0,0,0,0,0,0,0,0,0,0,0,0,0,0,0,0,0,0,0,0,0,0,0,0,0,0]}",
      "executable": false,
      "lamports": 2505600,
      "owner": "crcBwD7wUjzwsy8tJsVCzZvBTHeq5GoboGg84YraRyd",
      "rentEpoch": 0,
      "type": "stakeEntry",
      "parsed": {
        "bump": "254",
        "kind": "0",
        "pool": "Zdw34cuhqTAmkrMuFum6CCrx8fQNqNevAZMD4vVipmM",
        "amount": "0",
        "stakeMint": "9s9FHFgWXPrtZvY5nenfDfo9dc8z2sE7KbmDxv2GP7qM",
        "lastStaker": "11111111111111111111111111111111",
        "lastStakedAt": "1680172726",
        "lastUpdatedAt": "1691190931",
        "totalStakeSeconds": "10389114",
        "usedStakeSeconds": "0"
      }
    },
    {
      "pubkey": "7X5mXRYSHiHYp7MQfzXRZSnTHSVDfH2btXp8iCzMMb11",
      "data": "{\"type\":\"Buffer\",\"data\":[187,127,9,35,155,68,86,40,254,0,8,92,88,58,40,149,83,181,251,111,68,223,238,193,232,13,201,204,93,228,86,94,2,250,71,43,136,179,216,246,204,176,0,0,0,0,0,0,0,0,49,131,229,36,9,241,247,32,124,100,178,93,198,53,164,208,183,99,161,195,251,88,240,18,12,194,113,104,36,13,231,153,0,0,0,0,0,0,0,0,0,0,0,0,0,0,0,0,0,0,0,0,0,0,0,0,0,0,0,0,0,0,0,0,170,134,65,100,0,0,0,0,241,134,65,100,0,0,0,0,58,0,0,0,0,0,0,0,0,0,0,0,0,0,0,0,0,0,0,0,0,0,0,0,0,0,0,0,0,0,0,0,0,0,0,0,0,0,0,0,0,0,0,0,0,0,0,0,0,0,0,0,0,0,0,0,0,0,0,0,0,0,0,0,0,0,0,0,0,0,0,0,0,0,0,0,0,0,0,0,0,0,0,0,0,0,0,0,0,0,0,0,0,0,0,0,0,0,0,0,0,0]}",
      "executable": false,
      "lamports": 2505600,
      "owner": "crcBwD7wUjzwsy8tJsVCzZvBTHeq5GoboGg84YraRyd",
      "rentEpoch": 0,
      "type": "stakeEntry",
      "parsed": {
        "bump": "254",
        "kind": "0",
        "pool": "Zdw34cuhqTAmkrMuFum6CCrx8fQNqNevAZMD4vVipmM",
        "amount": "0",
        "stakeMint": "4LHdJRVh9yDT5tGK9wQtDVpr6G67S2ASedukdxEFLnoa",
        "lastStaker": "11111111111111111111111111111111",
        "lastStakedAt": "1682015914",
        "lastUpdatedAt": "1682015985",
        "totalStakeSeconds": "58",
        "usedStakeSeconds": "0"
      }
    },
    {
      "pubkey": "53XscWd516nhCAhJLhdhSAkciGiZevsRunem7yAzhvzZ",
      "data": "{\"type\":\"Buffer\",\"data\":[187,127,9,35,155,68,86,40,253,0,8,92,88,58,40,149,83,181,251,111,68,223,238,193,232,13,201,204,93,228,86,94,2,250,71,43,136,179,216,246,204,176,1,0,0,0,0,0,0,0,224,183,42,215,44,198,150,157,18,66,44,55,79,53,144,162,163,225,40,133,2,147,177,208,243,94,206,250,14,30,54,3,15,0,119,242,163,245,251,239,151,77,204,45,175,39,93,156,234,60,201,69,146,100,249,162,11,131,134,71,66,90,100,46,136,120,30,100,0,0,0,0,56,74,51,100,0,0,0,0,176,209,20,0,0,0,0,0,0,0,0,0,0,0,0,0,0,0,0,0,0,0,0,0,0,0,0,0,0,0,0,0,1,56,74,51,100,0,0,0,0,0,0,0,0,0,0,0,0,0,0,0,0,0,0,0,0,0,0,0,0,0,0,0,0,0,0,0,0,0,0,0,0,0,0,0,0,0,0,0,0,0,0,0,0,0,0,0,0,0,0,0,0,0,0,0,0,0,0,0,0,0]}",
      "executable": false,
      "lamports": 2505600,
      "owner": "crcBwD7wUjzwsy8tJsVCzZvBTHeq5GoboGg84YraRyd",
      "rentEpoch": 0,
      "type": "stakeEntry",
      "parsed": {
        "bump": "253",
        "kind": "0",
        "pool": "Zdw34cuhqTAmkrMuFum6CCrx8fQNqNevAZMD4vVipmM",
        "amount": "1",
        "stakeMint": "G8CKUC4mNEg6pYgrXvbw1LoNp7Yd5CHLztXod1TiArNe",
        "lastStaker": "21ZXjRHpgGrkSpUi8WvXXGHQgVwUhWcSm2mXzwgdWAHb",
        "lastStakedAt": "1679718536",
        "lastUpdatedAt": "1681082936",
        "totalStakeSeconds": "1364400",
        "usedStakeSeconds": "0",
        "cooldownStartSeconds": "1681082936"
      }
    },
    {
      "pubkey": "3L6zEsj31c439jWhkDbBtqbBrXF8arPwxz4dy57JKEj7",
      "data": "{\"type\":\"Buffer\",\"data\":[187,127,9,35,155,68,86,40,255,0,8,92,88,58,40,149,83,181,251,111,68,223,238,193,232,13,201,204,93,228,86,94,2,250,71,43,136,179,216,246,204,176,1,0,0,0,0,0,0,0,131,2,245,105,167,78,62,122,110,127,27,227,76,226,112,104,64,93,201,211,126,253,96,7,235,127,170,119,32,217,166,147,123,125,24,68,27,136,252,61,230,114,138,172,13,98,233,72,216,84,198,48,128,146,125,148,197,197,184,0,104,9,20,181,154,245,30,100,0,0,0,0,212,182,228,100,0,0,0,0,58,193,197,0,0,0,0,0,0,0,0,0,0,0,0,0,0,0,0,0,0,0,0,0,0,0,0,0,0,0,0,0,1,212,182,228,100,0,0,0,0,0,0,0,0,0,0,0,0,0,0,0,0,0,0,0,0,0,0,0,0,0,0,0,0,0,0,0,0,0,0,0,0,0,0,0,0,0,0,0,0,0,0,0,0,0,0,0,0,0,0,0,0,0,0,0,0,0,0,0,0,0]}",
      "executable": false,
      "lamports": 2505600,
      "owner": "crcBwD7wUjzwsy8tJsVCzZvBTHeq5GoboGg84YraRyd",
      "rentEpoch": 0,
      "type": "stakeEntry",
      "parsed": {
        "bump": "255",
        "kind": "0",
        "pool": "Zdw34cuhqTAmkrMuFum6CCrx8fQNqNevAZMD4vVipmM",
        "amount": "1",
        "stakeMint": "9pR2TFmHcYwLaVpaT1LfmUwUTzLahHpUkNPN8n6dD5TY",
        "lastStaker": "9K3nKG8ZripTqTGf2cUR5DuHUAEauZNqs4BusBBonGTE",
        "lastStakedAt": "1679750554",
        "lastUpdatedAt": "1692710612",
        "totalStakeSeconds": "12960058",
        "usedStakeSeconds": "0",
        "cooldownStartSeconds": "1692710612"
      }
    },
    {
      "pubkey": "RGB1FFo79itnnkVZXWfNt8qR71A7JtsoRDN9eYbo3V9",
      "data": "{\"type\":\"Buffer\",\"data\":[187,127,9,35,155,68,86,40,250,0,8,92,88,58,40,149,83,181,251,111,68,223,238,193,232,13,201,204,93,228,86,94,2,250,71,43,136,179,216,246,204,176,1,0,0,0,0,0,0,0,89,204,60,93,117,76,168,134,0,180,201,30,152,25,43,105,32,205,108,236,133,166,210,238,108,166,167,133,49,155,6,92,15,0,119,242,163,245,251,239,151,77,204,45,175,39,93,156,234,60,201,69,146,100,249,162,11,131,134,71,66,90,100,46,135,120,30,100,0,0,0,0,35,44,86,100,0,0,0,0,156,179,55,0,0,0,0,0,0,0,0,0,0,0,0,0,0,0,0,0,0,0,0,0,0,0,0,0,0,0,0,0,0,0,0,0,0,0,0,0,0,0,0,0,0,0,0,0,0,0,0,0,0,0,0,0,0,0,0,0,0,0,0,0,0,0,0,0,0,0,0,0,0,0,0,0,0,0,0,0,0,0,0,0,0,0,0,0,0,0,0,0,0,0,0,0,0,0,0,0,0,0]}",
      "executable": false,
      "lamports": 2505600,
      "owner": "crcBwD7wUjzwsy8tJsVCzZvBTHeq5GoboGg84YraRyd",
      "rentEpoch": 0,
      "type": "stakeEntry",
      "parsed": {
        "bump": "250",
        "kind": "0",
        "pool": "Zdw34cuhqTAmkrMuFum6CCrx8fQNqNevAZMD4vVipmM",
        "amount": "1",
        "stakeMint": "73XuuuVdsFq943X32Yv1ZsYVk4fNEV7mkngFc4GjHPaB",
        "lastStaker": "21ZXjRHpgGrkSpUi8WvXXGHQgVwUhWcSm2mXzwgdWAHb",
        "lastStakedAt": "1679718535",
        "lastUpdatedAt": "1683368995",
        "totalStakeSeconds": "3650460",
        "usedStakeSeconds": "0"
      }
    },
    {
      "pubkey": "C7aRTyuckZbDZPhpwrTV677TLtHv85232odE9f5ZNgCE",
      "data": "{\"type\":\"Buffer\",\"data\":[187,127,9,35,155,68,86,40,255,0,8,92,88,58,40,149,83,181,251,111,68,223,238,193,232,13,201,204,93,228,86,94,2,250,71,43,136,179,216,246,204,176,1,0,0,0,0,0,0,0,77,155,203,7,238,156,9,3,147,108,169,123,47,150,15,112,79,180,7,239,243,71,46,189,170,88,26,86,221,176,68,237,15,0,119,242,163,245,251,239,151,77,204,45,175,39,93,156,234,60,201,69,146,100,249,162,11,131,134,71,66,90,100,46,136,120,30,100,0,0,0,0,35,44,86,100,0,0,0,0,155,179,55,0,0,0,0,0,0,0,0,0,0,0,0,0,0,0,0,0,0,0,0,0,0,0,0,0,0,0,0,0,0,0,0,0,0,0,0,0,0,0,0,0,0,0,0,0,0,0,0,0,0,0,0,0,0,0,0,0,0,0,0,0,0,0,0,0,0,0,0,0,0,0,0,0,0,0,0,0,0,0,0,0,0,0,0,0,0,0,0,0,0,0,0,0,0,0,0,0,0,0]}",
      "executable": false,
      "lamports": 2505600,
      "owner": "crcBwD7wUjzwsy8tJsVCzZvBTHeq5GoboGg84YraRyd",
      "rentEpoch": 0,
      "type": "stakeEntry",
      "parsed": {
        "bump": "255",
        "kind": "0",
        "pool": "Zdw34cuhqTAmkrMuFum6CCrx8fQNqNevAZMD4vVipmM",
        "amount": "1",
        "stakeMint": "6DxBGBPKQEfMMA7PTYppsenGsXfkYDfTXCiGcfbao7CQ",
        "lastStaker": "21ZXjRHpgGrkSpUi8WvXXGHQgVwUhWcSm2mXzwgdWAHb",
        "lastStakedAt": "1679718536",
        "lastUpdatedAt": "1683368995",
        "totalStakeSeconds": "3650459",
        "usedStakeSeconds": "0"
      }
    },
    {
      "pubkey": "7NKu7gQNtxxyGrpNWx75QzzqYZA3xGtNu6XwVB33NfsT",
      "data": "{\"type\":\"Buffer\",\"data\":[187,127,9,35,155,68,86,40,255,0,8,92,88,58,40,149,83,181,251,111,68,223,238,193,232,13,201,204,93,228,86,94,2,250,71,43,136,179,216,246,204,176,1,0,0,0,0,0,0,0,109,120,210,216,242,196,24,21,5,133,61,169,63,125,193,132,18,95,154,167,62,26,55,240,164,85,218,69,46,47,46,186,66,161,115,240,189,250,184,87,117,144,226,86,145,157,67,244,57,21,211,157,219,15,139,119,118,206,21,33,180,40,154,100,150,206,63,100,0,0,0,0,108,69,94,100,0,0,0,0,214,118,30,0,0,0,0,0,0,0,0,0,0,0,0,0,0,0,0,0,0,0,0,0,0,0,0,0,0,0,0,0,0,0,0,0,0,0,0,0,0,0,0,0,0,0,0,0,0,0,0,0,0,0,0,0,0,0,0,0,0,0,0,0,0,0,0,0,0,0,0,0,0,0,0,0,0,0,0,0,0,0,0,0,0,0,0,0,0,0,0,0,0,0,0,0,0,0,0,0,0,0]}",
      "executable": false,
      "lamports": 2505600,
      "owner": "crcBwD7wUjzwsy8tJsVCzZvBTHeq5GoboGg84YraRyd",
      "rentEpoch": 0,
      "type": "stakeEntry",
      "parsed": {
        "bump": "255",
        "kind": "0",
        "pool": "Zdw34cuhqTAmkrMuFum6CCrx8fQNqNevAZMD4vVipmM",
        "amount": "1",
        "stakeMint": "8NLJB1sGSLYQ5yWjQ4x9ddyQT68DPyC9X3Bv1CVWpucM",
        "lastStaker": "5V6hURpiuXV1B3sYSWTTvg5t6RFJeqiQYJbQZ5WYT6eo",
        "lastStakedAt": "1681903254",
        "lastUpdatedAt": "1683899756",
        "totalStakeSeconds": "1996502",
        "usedStakeSeconds": "0"
      }
    },
    {
      "pubkey": "CZANdDMfNpDCmXPS42qApE3FaQPUjKnPMSDwxKG25TqV",
      "data": "{\"type\":\"Buffer\",\"data\":[187,127,9,35,155,68,86,40,255,0,8,92,88,58,40,149,83,181,251,111,68,223,238,193,232,13,201,204,93,228,86,94,2,250,71,43,136,179,216,246,204,176,1,0,0,0,0,0,0,0,245,71,195,228,63,66,197,193,72,80,32,174,64,73,216,26,157,34,240,131,108,108,71,199,207,175,198,145,50,12,14,115,123,125,24,68,27,136,252,61,230,114,138,172,13,98,233,72,216,84,198,48,128,146,125,148,197,197,184,0,104,9,20,181,154,245,30,100,0,0,0,0,212,182,228,100,0,0,0,0,58,193,197,0,0,0,0,0,0,0,0,0,0,0,0,0,0,0,0,0,0,0,0,0,0,0,0,0,0,0,0,0,1,212,182,228,100,0,0,0,0,0,0,0,0,0,0,0,0,0,0,0,0,0,0,0,0,0,0,0,0,0,0,0,0,0,0,0,0,0,0,0,0,0,0,0,0,0,0,0,0,0,0,0,0,0,0,0,0,0,0,0,0,0,0,0,0,0,0,0,0,0]}",
      "executable": false,
      "lamports": 2505600,
      "owner": "crcBwD7wUjzwsy8tJsVCzZvBTHeq5GoboGg84YraRyd",
      "rentEpoch": 0,
      "type": "stakeEntry",
      "parsed": {
        "bump": "255",
        "kind": "0",
        "pool": "Zdw34cuhqTAmkrMuFum6CCrx8fQNqNevAZMD4vVipmM",
        "amount": "1",
        "stakeMint": "HWUMcmRTJQ3bDR4ymyiEiLaQWuEzqw7NTck4zBm5BqLN",
        "lastStaker": "9K3nKG8ZripTqTGf2cUR5DuHUAEauZNqs4BusBBonGTE",
        "lastStakedAt": "1679750554",
        "lastUpdatedAt": "1692710612",
        "totalStakeSeconds": "12960058",
        "usedStakeSeconds": "0",
        "cooldownStartSeconds": "1692710612"
      }
    },
    {
      "pubkey": "9dyFhL5r4NEmmvVfrYMGsHHzFV2RGAYQJzpr5wPWEiVF",
      "data": "{\"type\":\"Buffer\",\"data\":[187,127,9,35,155,68,86,40,254,0,8,92,88,58,40,149,83,181,251,111,68,223,238,193,232,13,201,204,93,228,86,94,2,250,71,43,136,179,216,246,204,176,0,0,0,0,0,0,0,0,180,147,36,43,161,170,102,235,178,167,104,214,42,6,103,74,27,179,90,243,197,179,128,205,51,8,179,120,182,245,248,84,0,0,0,0,0,0,0,0,0,0,0,0,0,0,0,0,0,0,0,0,0,0,0,0,0,0,0,0,0,0,0,0,114,134,65,100,0,0,0,0,248,134,65,100,0,0,0,0,121,0,0,0,0,0,0,0,0,0,0,0,0,0,0,0,0,0,0,0,0,0,0,0,0,0,0,0,0,0,0,0,0,0,0,0,0,0,0,0,0,0,0,0,0,0,0,0,0,0,0,0,0,0,0,0,0,0,0,0,0,0,0,0,0,0,0,0,0,0,0,0,0,0,0,0,0,0,0,0,0,0,0,0,0,0,0,0,0,0,0,0,0,0,0,0,0,0,0,0,0,0]}",
      "executable": false,
      "lamports": 2505600,
      "owner": "crcBwD7wUjzwsy8tJsVCzZvBTHeq5GoboGg84YraRyd",
      "rentEpoch": 0,
      "type": "stakeEntry",
      "parsed": {
        "bump": "254",
        "kind": "0",
        "pool": "Zdw34cuhqTAmkrMuFum6CCrx8fQNqNevAZMD4vVipmM",
        "amount": "0",
        "stakeMint": "D9tX3td93knz559aMGchof5CfadKsC2rKnLgJWWjNDym",
        "lastStaker": "11111111111111111111111111111111",
        "lastStakedAt": "1682015858",
        "lastUpdatedAt": "1682015992",
        "totalStakeSeconds": "121",
        "usedStakeSeconds": "0"
      }
    },
    {
      "pubkey": "HsVhEuXQtcSsrbCvBkU11JU74oFF4PpFQNxqUYCqjdAM",
      "data": "{\"type\":\"Buffer\",\"data\":[187,127,9,35,155,68,86,40,255,0,8,92,88,58,40,149,83,181,251,111,68,223,238,193,232,13,201,204,93,228,86,94,2,250,71,43,136,179,216,246,204,176,1,0,0,0,0,0,0,0,126,149,58,197,104,18,170,166,104,159,165,216,169,214,86,170,157,16,217,176,207,56,191,79,73,170,19,59,218,56,102,223,123,125,24,68,27,136,252,61,230,114,138,172,13,98,233,72,216,84,198,48,128,146,125,148,197,197,184,0,104,9,20,181,154,245,30,100,0,0,0,0,212,182,228,100,0,0,0,0,58,193,197,0,0,0,0,0,0,0,0,0,0,0,0,0,0,0,0,0,0,0,0,0,0,0,0,0,0,0,0,0,1,212,182,228,100,0,0,0,0,0,0,0,0,0,0,0,0,0,0,0,0,0,0,0,0,0,0,0,0,0,0,0,0,0,0,0,0,0,0,0,0,0,0,0,0,0,0,0,0,0,0,0,0,0,0,0,0,0,0,0,0,0,0,0,0,0,0,0,0,0]}",
      "executable": false,
      "lamports": 2505600,
      "owner": "crcBwD7wUjzwsy8tJsVCzZvBTHeq5GoboGg84YraRyd",
      "rentEpoch": 0,
      "type": "stakeEntry",
      "parsed": {
        "bump": "255",
        "kind": "0",
        "pool": "Zdw34cuhqTAmkrMuFum6CCrx8fQNqNevAZMD4vVipmM",
        "amount": "1",
        "stakeMint": "9X8MG5dGiiobTEaZ1aAW71DjjGevhbho4im3pKaqpbmg",
        "lastStaker": "9K3nKG8ZripTqTGf2cUR5DuHUAEauZNqs4BusBBonGTE",
        "lastStakedAt": "1679750554",
        "lastUpdatedAt": "1692710612",
        "totalStakeSeconds": "12960058",
        "usedStakeSeconds": "0",
        "cooldownStartSeconds": "1692710612"
      }
    },
    {
      "pubkey": "7WvLp4syM7D3jQ51f9muxueMwAJaXsnRW4c7pArYd5pR",
      "data": "{\"type\":\"Buffer\",\"data\":[187,127,9,35,155,68,86,40,255,0,8,92,88,58,40,149,83,181,251,111,68,223,238,193,232,13,201,204,93,228,86,94,2,250,71,43,136,179,216,246,204,176,1,0,0,0,0,0,0,0,59,209,38,3,153,84,228,116,211,163,14,118,112,139,117,244,84,113,89,81,144,231,127,31,136,167,149,218,211,60,41,1,123,125,24,68,27,136,252,61,230,114,138,172,13,98,233,72,216,84,198,48,128,146,125,148,197,197,184,0,104,9,20,181,154,245,30,100,0,0,0,0,212,182,228,100,0,0,0,0,58,193,197,0,0,0,0,0,0,0,0,0,0,0,0,0,0,0,0,0,0,0,0,0,0,0,0,0,0,0,0,0,1,212,182,228,100,0,0,0,0,0,0,0,0,0,0,0,0,0,0,0,0,0,0,0,0,0,0,0,0,0,0,0,0,0,0,0,0,0,0,0,0,0,0,0,0,0,0,0,0,0,0,0,0,0,0,0,0,0,0,0,0,0,0,0,0,0,0,0,0,0]}",
      "executable": false,
      "lamports": 2505600,
      "owner": "crcBwD7wUjzwsy8tJsVCzZvBTHeq5GoboGg84YraRyd",
      "rentEpoch": 0,
      "type": "stakeEntry",
      "parsed": {
        "bump": "255",
        "kind": "0",
        "pool": "Zdw34cuhqTAmkrMuFum6CCrx8fQNqNevAZMD4vVipmM",
        "amount": "1",
        "stakeMint": "52W2Wz8MrPfYyKm9emxd1LqezMWmQENvJ4Qy5nvyQ8ek",
        "lastStaker": "9K3nKG8ZripTqTGf2cUR5DuHUAEauZNqs4BusBBonGTE",
        "lastStakedAt": "1679750554",
        "lastUpdatedAt": "1692710612",
        "totalStakeSeconds": "12960058",
        "usedStakeSeconds": "0",
        "cooldownStartSeconds": "1692710612"
      }
    },
    {
      "pubkey": "CZtJciFq51pqqfKUiQuMGPqdg1qXB5ssEScADnbA89Jg",
      "data": "{\"type\":\"Buffer\",\"data\":[187,127,9,35,155,68,86,40,255,0,8,92,88,58,40,149,83,181,251,111,68,223,238,193,232,13,201,204,93,228,86,94,2,250,71,43,136,179,216,246,204,176,1,0,0,0,0,0,0,0,67,112,74,49,87,237,129,152,211,186,195,225,205,34,111,103,249,169,236,79,78,144,133,126,171,246,206,150,33,183,146,110,151,22,110,100,183,216,144,62,40,98,104,84,89,46,60,168,26,238,184,23,192,172,103,35,153,234,200,139,151,44,212,130,13,122,36,100,0,0,0,0,3,247,78,100,0,0,0,0,246,124,42,0,0,0,0,0,0,0,0,0,0,0,0,0,0,0,0,0,0,0,0,0,0,0,0,0,0,0,0,0,0,0,0,0,0,0,0,0,0,0,0,0,0,0,0,0,0,0,0,0,0,0,0,0,0,0,0,0,0,0,0,0,0,0,0,0,0,0,0,0,0,0,0,0,0,0,0,0,0,0,0,0,0,0,0,0,0,0,0,0,0,0,0,0,0,0,0,0,0,0]}",
      "executable": false,
      "lamports": 2505600,
      "owner": "crcBwD7wUjzwsy8tJsVCzZvBTHeq5GoboGg84YraRyd",
      "rentEpoch": 0,
      "type": "stakeEntry",
      "parsed": {
        "bump": "255",
        "kind": "0",
        "pool": "Zdw34cuhqTAmkrMuFum6CCrx8fQNqNevAZMD4vVipmM",
        "amount": "1",
        "stakeMint": "5YFdGxHkZn4NaBraXKx9vRZ85xKezoq3MrQk5X8pgUtm",
        "lastStaker": "BAnQEniNyqYGAAnHXumWjNKxPyXTCotpGQ7ddDwrXyr9",
        "lastStakedAt": "1680112141",
        "lastUpdatedAt": "1682896643",
        "totalStakeSeconds": "2784502",
        "usedStakeSeconds": "0"
      }
    },
    {
      "pubkey": "G3ABamzDA3MmzmR4QH4NYF5biBBAZG35FgWbtm7ej8Pj",
      "data": "{\"type\":\"Buffer\",\"data\":[187,127,9,35,155,68,86,40,254,0,8,92,88,58,40,149,83,181,251,111,68,223,238,193,232,13,201,204,93,228,86,94,2,250,71,43,136,179,216,246,204,176,1,0,0,0,0,0,0,0,198,197,6,67,25,65,86,203,47,67,8,27,144,0,89,53,83,131,240,45,208,107,209,90,52,11,95,211,108,171,150,230,15,0,119,242,163,245,251,239,151,77,204,45,175,39,93,156,234,60,201,69,146,100,249,162,11,131,134,71,66,90,100,46,135,120,30,100,0,0,0,0,35,44,86,100,0,0,0,0,156,179,55,0,0,0,0,0,0,0,0,0,0,0,0,0,0,0,0,0,0,0,0,0,0,0,0,0,0,0,0,0,0,0,0,0,0,0,0,0,0,0,0,0,0,0,0,0,0,0,0,0,0,0,0,0,0,0,0,0,0,0,0,0,0,0,0,0,0,0,0,0,0,0,0,0,0,0,0,0,0,0,0,0,0,0,0,0,0,0,0,0,0,0,0,0,0,0,0,0,0,0]}",
      "executable": false,
      "lamports": 2505600,
      "owner": "crcBwD7wUjzwsy8tJsVCzZvBTHeq5GoboGg84YraRyd",
      "rentEpoch": 0,
      "type": "stakeEntry",
      "parsed": {
        "bump": "254",
        "kind": "0",
        "pool": "Zdw34cuhqTAmkrMuFum6CCrx8fQNqNevAZMD4vVipmM",
        "amount": "1",
        "stakeMint": "ENuyU9vWuZ36RUqXBzyM6TEUfoX9jAwboJjEXHpLXcSH",
        "lastStaker": "21ZXjRHpgGrkSpUi8WvXXGHQgVwUhWcSm2mXzwgdWAHb",
        "lastStakedAt": "1679718535",
        "lastUpdatedAt": "1683368995",
        "totalStakeSeconds": "3650460",
        "usedStakeSeconds": "0"
      }
    },
    {
      "pubkey": "DbrP7PN1tCTvke1tkrmMfK1niqa5SosrPb9FzbvDn9ty",
      "data": "{\"type\":\"Buffer\",\"data\":[187,127,9,35,155,68,86,40,255,0,8,92,88,58,40,149,83,181,251,111,68,223,238,193,232,13,201,204,93,228,86,94,2,250,71,43,136,179,216,246,204,176,1,0,0,0,0,0,0,0,52,30,13,249,103,183,125,38,147,129,150,108,65,63,203,209,45,10,141,82,108,128,115,255,210,130,242,165,35,251,134,47,123,125,24,68,27,136,252,61,230,114,138,172,13,98,233,72,216,84,198,48,128,146,125,148,197,197,184,0,104,9,20,181,154,245,30,100,0,0,0,0,212,182,228,100,0,0,0,0,58,193,197,0,0,0,0,0,0,0,0,0,0,0,0,0,0,0,0,0,0,0,0,0,0,0,0,0,0,0,0,0,1,212,182,228,100,0,0,0,0,0,0,0,0,0,0,0,0,0,0,0,0,0,0,0,0,0,0,0,0,0,0,0,0,0,0,0,0,0,0,0,0,0,0,0,0,0,0,0,0,0,0,0,0,0,0,0,0,0,0,0,0,0,0,0,0,0,0,0,0,0]}",
      "executable": false,
      "lamports": 2505600,
      "owner": "crcBwD7wUjzwsy8tJsVCzZvBTHeq5GoboGg84YraRyd",
      "rentEpoch": 0,
      "type": "stakeEntry",
      "parsed": {
        "bump": "255",
        "kind": "0",
        "pool": "Zdw34cuhqTAmkrMuFum6CCrx8fQNqNevAZMD4vVipmM",
        "amount": "1",
        "stakeMint": "4WSnHKPh28YXsDcTfjm5WuEahf6VJLzP5pLgqb91TH74",
        "lastStaker": "9K3nKG8ZripTqTGf2cUR5DuHUAEauZNqs4BusBBonGTE",
        "lastStakedAt": "1679750554",
        "lastUpdatedAt": "1692710612",
        "totalStakeSeconds": "12960058",
        "usedStakeSeconds": "0",
        "cooldownStartSeconds": "1692710612"
      }
    },
    {
      "pubkey": "BCGvNs9Mfn4ub1kadwpAVaJ4CWJi8whQWB1MpEaRgXXQ",
      "data": "{\"type\":\"Buffer\",\"data\":[187,127,9,35,155,68,86,40,252,0,8,92,88,58,40,149,83,181,251,111,68,223,238,193,232,13,201,204,93,228,86,94,2,250,71,43,136,179,216,246,204,176,0,0,0,0,0,0,0,0,21,78,195,130,121,46,208,218,69,189,219,58,232,161,165,235,116,90,132,135,137,158,68,93,173,36,196,207,139,51,173,219,0,0,0,0,0,0,0,0,0,0,0,0,0,0,0,0,0,0,0,0,0,0,0,0,0,0,0,0,0,0,0,0,91,134,65,100,0,0,0,0,12,135,65,100,0,0,0,0,37,1,0,0,0,0,0,0,0,0,0,0,0,0,0,0,0,0,0,0,0,0,0,0,0,0,0,0,0,0,0,0,0,0,0,0,0,0,0,0,0,0,0,0,0,0,0,0,0,0,0,0,0,0,0,0,0,0,0,0,0,0,0,0,0,0,0,0,0,0,0,0,0,0,0,0,0,0,0,0,0,0,0,0,0,0,0,0,0,0,0,0,0,0,0,0,0,0,0,0,0,0]}",
      "executable": false,
      "lamports": 2505600,
      "owner": "crcBwD7wUjzwsy8tJsVCzZvBTHeq5GoboGg84YraRyd",
      "rentEpoch": 0,
      "type": "stakeEntry",
      "parsed": {
        "bump": "252",
        "kind": "0",
        "pool": "Zdw34cuhqTAmkrMuFum6CCrx8fQNqNevAZMD4vVipmM",
        "amount": "0",
        "stakeMint": "2SBDoMjzaHtexTisjnCnYMsQhrTxGA32RReNcKTJTmwG",
        "lastStaker": "11111111111111111111111111111111",
        "lastStakedAt": "1682015835",
        "lastUpdatedAt": "1682016012",
        "totalStakeSeconds": "293",
        "usedStakeSeconds": "0"
      }
    },
    {
      "pubkey": "ELCrfygEw87MZzg9wbSyp9MbEHTguMthWwk5YrR3joBF",
      "data": "{\"type\":\"Buffer\",\"data\":[187,127,9,35,155,68,86,40,254,0,8,92,88,58,40,149,83,181,251,111,68,223,238,193,232,13,201,204,93,228,86,94,2,250,71,43,136,179,216,246,204,176,1,0,0,0,0,0,0,0,109,93,49,234,110,96,55,178,80,23,21,46,251,189,44,91,41,243,41,52,241,132,166,19,177,183,251,121,252,49,158,250,90,122,247,107,49,170,119,117,231,187,187,19,170,231,227,86,5,115,135,67,159,157,88,131,20,47,141,50,161,151,155,82,228,15,36,100,0,0,0,0,145,204,167,100,0,0,0,0,173,188,131,0,0,0,0,0,0,0,0,0,0,0,0,0,0,0,0,0,0,0,0,0,0,0,0,0,0,0,0,0,1,145,204,167,100,0,0,0,0,0,0,0,0,0,0,0,0,0,0,0,0,0,0,0,0,0,0,0,0,0,0,0,0,0,0,0,0,0,0,0,0,0,0,0,0,0,0,0,0,0,0,0,0,0,0,0,0,0,0,0,0,0,0,0,0,0,0,0,0,0]}",
      "executable": false,
      "lamports": 2505600,
      "owner": "crcBwD7wUjzwsy8tJsVCzZvBTHeq5GoboGg84YraRyd",
      "rentEpoch": 0,
      "type": "stakeEntry",
      "parsed": {
        "bump": "254",
        "kind": "0",
        "pool": "Zdw34cuhqTAmkrMuFum6CCrx8fQNqNevAZMD4vVipmM",
        "amount": "1",
        "stakeMint": "8MurwywMp2tvVo2AJNshJo9kLBgt5mWzxJx8DkPhBfvH",
        "lastStaker": "76CSouD3eC8PRMXXj9u2Es5DYngLyChH3PNcbmEQHSSM",
        "lastStakedAt": "1680084964",
        "lastUpdatedAt": "1688718481",
        "totalStakeSeconds": "8633517",
        "usedStakeSeconds": "0",
        "cooldownStartSeconds": "1688718481"
      }
    },
    {
      "pubkey": "HiMZKJqMK2FicjMwiLeR3QfevKc8HJQtgssVYdqa7jBP",
      "data": "{\"type\":\"Buffer\",\"data\":[187,127,9,35,155,68,86,40,255,0,8,92,88,58,40,149,83,181,251,111,68,223,238,193,232,13,201,204,93,228,86,94,2,250,71,43,136,179,216,246,204,176,1,0,0,0,0,0,0,0,110,7,193,212,242,27,82,39,131,104,79,210,110,86,13,122,166,208,23,19,7,147,156,210,48,198,128,36,94,207,187,179,123,125,24,68,27,136,252,61,230,114,138,172,13,98,233,72,216,84,198,48,128,146,125,148,197,197,184,0,104,9,20,181,154,245,30,100,0,0,0,0,212,182,228,100,0,0,0,0,58,193,197,0,0,0,0,0,0,0,0,0,0,0,0,0,0,0,0,0,0,0,0,0,0,0,0,0,0,0,0,0,1,212,182,228,100,0,0,0,0,0,0,0,0,0,0,0,0,0,0,0,0,0,0,0,0,0,0,0,0,0,0,0,0,0,0,0,0,0,0,0,0,0,0,0,0,0,0,0,0,0,0,0,0,0,0,0,0,0,0,0,0,0,0,0,0,0,0,0,0,0]}",
      "executable": false,
      "lamports": 2505600,
      "owner": "crcBwD7wUjzwsy8tJsVCzZvBTHeq5GoboGg84YraRyd",
      "rentEpoch": 0,
      "type": "stakeEntry",
      "parsed": {
        "bump": "255",
        "kind": "0",
        "pool": "Zdw34cuhqTAmkrMuFum6CCrx8fQNqNevAZMD4vVipmM",
        "amount": "1",
        "stakeMint": "8QWi26PRMQdZr6D3tkK7m9Lsucd9seP1DzzEVdMeEMqk",
        "lastStaker": "9K3nKG8ZripTqTGf2cUR5DuHUAEauZNqs4BusBBonGTE",
        "lastStakedAt": "1679750554",
        "lastUpdatedAt": "1692710612",
        "totalStakeSeconds": "12960058",
        "usedStakeSeconds": "0",
        "cooldownStartSeconds": "1692710612"
      }
    },
    {
      "pubkey": "6XHzvhfG9DErfkKXw3H1W27jrJZ22pzf49zLF1ZFA48m",
      "data": "{\"type\":\"Buffer\",\"data\":[187,127,9,35,155,68,86,40,253,0,8,92,88,58,40,149,83,181,251,111,68,223,238,193,232,13,201,204,93,228,86,94,2,250,71,43,136,179,216,246,204,176,1,0,0,0,0,0,0,0,48,227,184,220,59,137,141,87,133,75,106,159,85,189,76,168,35,178,220,145,113,253,255,49,29,73,241,15,36,56,17,86,209,216,129,145,37,111,68,177,27,135,35,102,155,120,34,4,0,33,29,241,138,232,3,64,232,30,72,50,197,94,240,49,117,55,34,100,0,0,0,0,117,55,34,100,0,0,0,0,0,0,0,0,0,0,0,0,0,0,0,0,0,0,0,0,0,0,0,0,0,0,0,0,0,0,0,0,0,0,0,0,0,0,0,0,0,0,0,0,0,0,0,0,0,0,0,0,0,0,0,0,0,0,0,0,0,0,0,0,0,0,0,0,0,0,0,0,0,0,0,0,0,0,0,0,0,0,0,0,0,0,0,0,0,0,0,0,0,0,0,0,0,0,0,0,0,0,0,0,0,0]}",
      "executable": false,
      "lamports": 2505600,
      "owner": "crcBwD7wUjzwsy8tJsVCzZvBTHeq5GoboGg84YraRyd",
      "rentEpoch": 0,
      "type": "stakeEntry",
      "parsed": {
        "bump": "253",
        "kind": "0",
        "pool": "Zdw34cuhqTAmkrMuFum6CCrx8fQNqNevAZMD4vVipmM",
        "amount": "1",
        "stakeMint": "4Hqy9dJyUF4idnpf5wNEP7MDMcnRzCynjcFxf7QaHGSZ",
        "lastStaker": "F89guEx13xqRvTbA8CT2EoacvnVskRZDDVoETB6Qc4Ki",
        "lastStakedAt": "1679964021",
        "lastUpdatedAt": "1679964021",
        "totalStakeSeconds": "0",
        "usedStakeSeconds": "0"
      }
    },
    {
      "pubkey": "DB8BrChqomi6DhMpmb1fFewEWXZ2tXaVCR48q2H6E5yK",
      "data": "{\"type\":\"Buffer\",\"data\":[187,127,9,35,155,68,86,40,255,0,8,92,88,58,40,149,83,181,251,111,68,223,238,193,232,13,201,204,93,228,86,94,2,250,71,43,136,179,216,246,204,176,1,0,0,0,0,0,0,0,26,43,137,183,65,107,180,66,254,212,3,199,25,20,218,254,188,26,248,215,210,235,72,97,73,252,51,249,33,71,8,40,180,120,38,241,80,198,83,138,50,24,104,17,85,43,191,214,187,247,171,184,99,57,35,253,214,45,92,176,171,64,145,193,239,83,50,100,0,0,0,0,239,83,50,100,0,0,0,0,0,0,0,0,0,0,0,0,0,0,0,0,0,0,0,0,0,0,0,0,0,0,0,0,0,0,0,0,0,0,0,0,0,0,0,0,0,0,0,0,0,0,0,0,0,0,0,0,0,0,0,0,0,0,0,0,0,0,0,0,0,0,0,0,0,0,0,0,0,0,0,0,0,0,0,0,0,0,0,0,0,0,0,0,0,0,0,0,0,0,0,0,0,0,0,0,0,0,0,0,0,0]}",
      "executable": false,
      "lamports": 2505600,
      "owner": "crcBwD7wUjzwsy8tJsVCzZvBTHeq5GoboGg84YraRyd",
      "rentEpoch": 0,
      "type": "stakeEntry",
      "parsed": {
        "bump": "255",
        "kind": "0",
        "pool": "Zdw34cuhqTAmkrMuFum6CCrx8fQNqNevAZMD4vVipmM",
        "amount": "1",
        "stakeMint": "2mA77KhWFK9Uk4KMRkKikJUCVFec9Uxoj9VjmabhDVV1",
        "lastStaker": "D9UedN7KHbQL5Ks5pwVg6vnrEJqptwQQcdqAHreayK9z",
        "lastStakedAt": "1681019887",
        "lastUpdatedAt": "1681019887",
        "totalStakeSeconds": "0",
        "usedStakeSeconds": "0"
      }
    },
    {
      "pubkey": "Gpxf45crqeu2fGTYTfHR2PkAvUYEcTqzUGxeufdS1Q6G",
      "data": "{\"type\":\"Buffer\",\"data\":[187,127,9,35,155,68,86,40,254,0,8,92,88,58,40,149,83,181,251,111,68,223,238,193,232,13,201,204,93,228,86,94,2,250,71,43,136,179,216,246,204,176,1,0,0,0,0,0,0,0,218,148,138,125,100,19,85,123,172,46,243,107,200,184,85,139,37,234,220,218,237,85,174,70,84,56,66,151,164,37,105,253,123,125,24,68,27,136,252,61,230,114,138,172,13,98,233,72,216,84,198,48,128,146,125,148,197,197,184,0,104,9,20,181,154,245,30,100,0,0,0,0,210,182,228,100,0,0,0,0,56,193,197,0,0,0,0,0,0,0,0,0,0,0,0,0,0,0,0,0,0,0,0,0,0,0,0,0,0,0,0,0,1,210,182,228,100,0,0,0,0,0,0,0,0,0,0,0,0,0,0,0,0,0,0,0,0,0,0,0,0,0,0,0,0,0,0,0,0,0,0,0,0,0,0,0,0,0,0,0,0,0,0,0,0,0,0,0,0,0,0,0,0,0,0,0,0,0,0,0,0,0]}",
      "executable": false,
      "lamports": 2505600,
      "owner": "crcBwD7wUjzwsy8tJsVCzZvBTHeq5GoboGg84YraRyd",
      "rentEpoch": 0,
      "type": "stakeEntry",
      "parsed": {
        "bump": "254",
        "kind": "0",
        "pool": "Zdw34cuhqTAmkrMuFum6CCrx8fQNqNevAZMD4vVipmM",
        "amount": "1",
        "stakeMint": "FiFFQy7D6Ghfm9ixBz2kHcgToHJ28vTNa2MnCXPhhz36",
        "lastStaker": "9K3nKG8ZripTqTGf2cUR5DuHUAEauZNqs4BusBBonGTE",
        "lastStakedAt": "1679750554",
        "lastUpdatedAt": "1692710610",
        "totalStakeSeconds": "12960056",
        "usedStakeSeconds": "0",
        "cooldownStartSeconds": "1692710610"
      }
    }
  ],
  "rewardEntries": [
    {
      "pubkey": "4XoDgWXshjngBnjiXvjkgp35Quaj4KzcXuxh2kPaetgo",
      "data": "{\"type\":\"Buffer\",\"data\":[208,191,173,14,213,84,179,162,255,198,19,95,26,247,78,118,178,28,247,186,4,61,158,157,212,251,46,43,128,114,95,196,174,146,114,135,215,109,206,68,58,165,153,180,36,163,133,194,88,3,142,63,84,36,29,107,156,223,14,115,136,160,216,118,95,178,33,53,153,153,39,17,65,242,83,105,0,0,0,0,0,0,0,0,0,0,0,0,0,1,0,0,0,0,0,0,0,0,0,0,0,0,0,0,0,0,0,0,0,0,0,0,0,0,0,0,0,0,0,0,0,0,0,0,0,0,0,0,0,0,0,0,0,0,0,0,0,0,0,0,0,0,0,0,0,0,0,0,0,0,0,0,0,0,0,0,0,0,0,0,0,0,0,0,0,0,0,0]}",
      "executable": false,
      "lamports": 2060160,
      "owner": "crcBwD7wUjzwsy8tJsVCzZvBTHeq5GoboGg84YraRyd",
      "rentEpoch": 0,
      "type": "rewardEntry",
      "parsed": {
        "bump": "255",
        "stakeEntry": "ELCrfygEw87MZzg9wbSyp9MbEHTguMthWwk5YrR3joBF",
        "rewardDistributor": "C9SCyVUfoNJnYQDWgWN8CHQErjo7oNeRZk4kePJR7Cak",
        "rewardSecondsReceived": "6902770",
        "multiplier": "1"
      }
    },
    {
      "pubkey": "H9UY4Q7V93he9DCrgf6vjiu4Q4tys7MJcKgTfS9qGz2x",
      "data": "{\"type\":\"Buffer\",\"data\":[208,191,173,14,213,84,179,162,252,223,108,217,32,48,27,83,37,252,180,232,210,79,155,36,253,226,164,226,174,14,244,189,28,226,110,144,60,18,197,219,66,165,153,180,36,163,133,194,88,3,142,63,84,36,29,107,156,223,14,115,136,160,216,118,95,178,33,53,153,153,39,17,65,156,179,55,0,0,0,0,0,0,0,0,0,0,0,0,0,1,0,0,0,0,0,0,0,0,0,0,0,0,0,0,0,0,0,0,0,0,0,0,0,0,0,0,0,0,0,0,0,0,0,0,0,0,0,0,0,0,0,0,0,0,0,0,0,0,0,0,0,0,0,0,0,0,0,0,0,0,0,0,0,0,0,0,0,0,0,0,0,0,0,0,0,0,0,0]}",
      "executable": false,
      "lamports": 2060160,
      "owner": "crcBwD7wUjzwsy8tJsVCzZvBTHeq5GoboGg84YraRyd",
      "rentEpoch": 0,
      "type": "rewardEntry",
      "parsed": {
        "bump": "252",
        "stakeEntry": "G3ABamzDA3MmzmR4QH4NYF5biBBAZG35FgWbtm7ej8Pj",
        "rewardDistributor": "C9SCyVUfoNJnYQDWgWN8CHQErjo7oNeRZk4kePJR7Cak",
        "rewardSecondsReceived": "3650460",
        "multiplier": "1"
      }
    },
    {
      "pubkey": "HRi19J55XsEdJGDTGhmwJRFJoSiMKk8qwSVYVCtA7EKV",
      "data": "{\"type\":\"Buffer\",\"data\":[208,191,173,14,213,84,179,162,254,96,218,239,200,3,148,64,109,99,138,233,213,121,131,174,84,26,62,7,17,37,169,74,62,149,185,50,159,28,204,112,8,165,153,180,36,163,133,194,88,3,142,63,84,36,29,107,156,223,14,115,136,160,216,118,95,178,33,53,153,153,39,17,65,50,0,0,0,0,0,0,0,0,0,0,0,0,0,0,0,1,0,0,0,0,0,0,0,0,0,0,0,0,0,0,0,0,0,0,0,0,0,0,0,0,0,0,0,0,0,0,0,0,0,0,0,0,0,0,0,0,0,0,0,0,0,0,0,0,0,0,0,0,0,0,0,0,0,0,0,0,0,0,0,0,0,0,0,0,0,0,0,0,0,0,0,0,0,0]}",
      "executable": false,
      "lamports": 2060160,
      "owner": "crcBwD7wUjzwsy8tJsVCzZvBTHeq5GoboGg84YraRyd",
      "rentEpoch": 0,
      "type": "rewardEntry",
      "parsed": {
        "bump": "254",
        "stakeEntry": "7X5mXRYSHiHYp7MQfzXRZSnTHSVDfH2btXp8iCzMMb11",
        "rewardDistributor": "C9SCyVUfoNJnYQDWgWN8CHQErjo7oNeRZk4kePJR7Cak",
        "rewardSecondsReceived": "50",
        "multiplier": "1"
      }
    },
    {
      "pubkey": "GAV4w4bR5zCTFbYgd58sjyPREj1YmZXX1Bx96vPsNv4W",
      "data": "{\"type\":\"Buffer\",\"data\":[208,191,173,14,213,84,179,162,255,96,208,71,78,23,7,107,219,85,215,217,253,37,78,166,37,1,30,216,212,149,71,24,242,253,110,99,82,3,24,83,62,165,153,180,36,163,133,194,88,3,142,63,84,36,29,107,156,223,14,115,136,160,216,118,95,178,33,53,153,153,39,17,65,0,0,0,0,0,0,0,0,0,0,0,0,0,0,0,0,1,0,0,0,0,0,0,0,0,0,0,0,0,0,0,0,0,0,0,0,0,0,0,0,0,0,0,0,0,0,0,0,0,0,0,0,0,0,0,0,0,0,0,0,0,0,0,0,0,0,0,0,0,0,0,0,0,0,0,0,0,0,0,0,0,0,0,0,0,0,0,0,0,0,0,0,0,0,0]}",
      "executable": false,
      "lamports": 2060160,
      "owner": "crcBwD7wUjzwsy8tJsVCzZvBTHeq5GoboGg84YraRyd",
      "rentEpoch": 0,
      "type": "rewardEntry",
      "parsed": {
        "bump": "255",
        "stakeEntry": "7WvLp4syM7D3jQ51f9muxueMwAJaXsnRW4c7pArYd5pR",
        "rewardDistributor": "C9SCyVUfoNJnYQDWgWN8CHQErjo7oNeRZk4kePJR7Cak",
        "rewardSecondsReceived": "0",
        "multiplier": "1"
      }
    },
    {
      "pubkey": "8Jatj5cieUxrQnQKuqaB4hVpKFdE9etvXdFQuMzMjTRz",
      "data": "{\"type\":\"Buffer\",\"data\":[208,191,173,14,213,84,179,162,255,60,20,209,46,64,174,73,87,220,78,85,195,25,225,127,230,246,214,97,222,37,1,168,135,199,22,51,127,212,223,101,238,165,153,180,36,163,133,194,88,3,142,63,84,36,29,107,156,223,14,115,136,160,216,118,95,178,33,53,153,153,39,17,65,176,209,20,0,0,0,0,0,0,0,0,0,0,0,0,0,1,0,0,0,0,0,0,0,0,0,0,0,0,0,0,0,0,0,0,0,0,0,0,0,0,0,0,0,0,0,0,0,0,0,0,0,0,0,0,0,0,0,0,0,0,0,0,0,0,0,0,0,0,0,0,0,0,0,0,0,0,0,0,0,0,0,0,0,0,0,0,0,0,0,0,0,0,0,0]}",
      "executable": false,
      "lamports": 2060160,
      "owner": "crcBwD7wUjzwsy8tJsVCzZvBTHeq5GoboGg84YraRyd",
      "rentEpoch": 0,
      "type": "rewardEntry",
      "parsed": {
        "bump": "255",
        "stakeEntry": "53XscWd516nhCAhJLhdhSAkciGiZevsRunem7yAzhvzZ",
        "rewardDistributor": "C9SCyVUfoNJnYQDWgWN8CHQErjo7oNeRZk4kePJR7Cak",
        "rewardSecondsReceived": "1364400",
        "multiplier": "1"
      }
    },
    {
      "pubkey": "Hxv7iR2GDXaU3TuSfxtGvkwnP1CZ9ZrUFcBbMk5m54Kd",
      "data": "{\"type\":\"Buffer\",\"data\":[208,191,173,14,213,84,179,162,255,165,31,212,202,37,128,243,26,37,60,29,233,126,178,89,122,127,36,217,143,57,219,136,239,92,155,25,173,233,183,55,79,165,153,180,36,163,133,194,88,3,142,63,84,36,29,107,156,223,14,115,136,160,216,118,95,178,33,53,153,153,39,17,65,146,179,55,0,0,0,0,0,0,0,0,0,0,0,0,0,1,0,0,0,0,0,0,0,0,0,0,0,0,0,0,0,0,0,0,0,0,0,0,0,0,0,0,0,0,0,0,0,0,0,0,0,0,0,0,0,0,0,0,0,0,0,0,0,0,0,0,0,0,0,0,0,0,0,0,0,0,0,0,0,0,0,0,0,0,0,0,0,0,0,0,0,0,0,0]}",
      "executable": false,
      "lamports": 2060160,
      "owner": "crcBwD7wUjzwsy8tJsVCzZvBTHeq5GoboGg84YraRyd",
      "rentEpoch": 0,
      "type": "rewardEntry",
      "parsed": {
        "bump": "255",
        "stakeEntry": "C7aRTyuckZbDZPhpwrTV677TLtHv85232odE9f5ZNgCE",
        "rewardDistributor": "C9SCyVUfoNJnYQDWgWN8CHQErjo7oNeRZk4kePJR7Cak",
        "rewardSecondsReceived": "3650450",
        "multiplier": "1"
      }
    },
    {
      "pubkey": "Bpv8fzyTw4GgvWbgKF9pr1MPyyPvw1cvc4CiHLCR72pr",
      "data": "{\"type\":\"Buffer\",\"data\":[208,191,173,14,213,84,179,162,255,34,156,45,185,188,169,30,125,215,42,232,233,181,30,223,58,166,201,166,238,140,67,80,159,20,254,9,151,28,148,253,254,165,153,180,36,163,133,194,88,3,142,63,84,36,29,107,156,223,14,115,136,160,216,118,95,178,33,53,153,153,39,17,65,0,0,0,0,0,0,0,0,0,0,0,0,0,0,0,0,1,0,0,0,0,0,0,0,0,0,0,0,0,0,0,0,0,0,0,0,0,0,0,0,0,0,0,0,0,0,0,0,0,0,0,0,0,0,0,0,0,0,0,0,0,0,0,0,0,0,0,0,0,0,0,0,0,0,0,0,0,0,0,0,0,0,0,0,0,0,0,0,0,0,0,0,0,0,0]}",
      "executable": false,
      "lamports": 2060160,
      "owner": "crcBwD7wUjzwsy8tJsVCzZvBTHeq5GoboGg84YraRyd",
      "rentEpoch": 0,
      "type": "rewardEntry",
      "parsed": {
        "bump": "255",
        "stakeEntry": "3L6zEsj31c439jWhkDbBtqbBrXF8arPwxz4dy57JKEj7",
        "rewardDistributor": "C9SCyVUfoNJnYQDWgWN8CHQErjo7oNeRZk4kePJR7Cak",
        "rewardSecondsReceived": "0",
        "multiplier": "1"
      }
    },
    {
      "pubkey": "26DpSrogi9PM3esntr4adMmKBiVxEbAghNueaQVfEoPK",
      "data": "{\"type\":\"Buffer\",\"data\":[208,191,173,14,213,84,179,162,255,171,173,189,111,38,200,128,223,46,17,53,190,187,42,86,92,136,212,106,237,63,103,68,183,35,194,88,21,207,156,62,180,165,153,180,36,163,133,194,88,3,142,63,84,36,29,107,156,223,14,115,136,160,216,118,95,178,33,53,153,153,39,17,65,0,0,0,0,0,0,0,0,0,0,0,0,0,0,0,0,1,0,0,0,0,0,0,0,0,0,0,0,0,0,0,0,0,0,0,0,0,0,0,0,0,0,0,0,0,0,0,0,0,0,0,0,0,0,0,0,0,0,0,0,0,0,0,0,0,0,0,0,0,0,0,0,0,0,0,0,0,0,0,0,0,0,0,0,0,0,0,0,0,0,0,0,0,0,0]}",
      "executable": false,
      "lamports": 2060160,
      "owner": "crcBwD7wUjzwsy8tJsVCzZvBTHeq5GoboGg84YraRyd",
      "rentEpoch": 0,
      "type": "rewardEntry",
      "parsed": {
        "bump": "255",
        "stakeEntry": "CZANdDMfNpDCmXPS42qApE3FaQPUjKnPMSDwxKG25TqV",
        "rewardDistributor": "C9SCyVUfoNJnYQDWgWN8CHQErjo7oNeRZk4kePJR7Cak",
        "rewardSecondsReceived": "0",
        "multiplier": "1"
      }
    },
    {
      "pubkey": "Ey2ggUiebbZ3BtJYa4LTpMcPvaFbM3bPQN3sXXTGA2Us",
      "data": "{\"type\":\"Buffer\",\"data\":[208,191,173,14,213,84,179,162,254,248,83,12,77,97,255,93,49,222,20,236,63,217,152,186,129,182,83,148,86,116,138,197,169,120,75,61,78,4,125,202,194,165,153,180,36,163,133,194,88,3,142,63,84,36,29,107,156,223,14,115,136,160,216,118,95,178,33,53,153,153,39,17,65,0,0,0,0,0,0,0,0,0,0,0,0,0,0,0,0,1,0,0,0,0,0,0,0,0,0,0,0,0,0,0,0,0,0,0,0,0,0,0,0,0,0,0,0,0,0,0,0,0,0,0,0,0,0,0,0,0,0,0,0,0,0,0,0,0,0,0,0,0,0,0,0,0,0,0,0,0,0,0,0,0,0,0,0,0,0,0,0,0,0,0,0,0,0,0]}",
      "executable": false,
      "lamports": 2060160,
      "owner": "crcBwD7wUjzwsy8tJsVCzZvBTHeq5GoboGg84YraRyd",
      "rentEpoch": 0,
      "type": "rewardEntry",
      "parsed": {
        "bump": "254",
        "stakeEntry": "HiMZKJqMK2FicjMwiLeR3QfevKc8HJQtgssVYdqa7jBP",
        "rewardDistributor": "C9SCyVUfoNJnYQDWgWN8CHQErjo7oNeRZk4kePJR7Cak",
        "rewardSecondsReceived": "0",
        "multiplier": "1"
      }
    },
    {
      "pubkey": "7PTB7VYFq1jVHZXey7Poq91Y3ejGRbKA95SafdUvhhtX",
      "data": "{\"type\":\"Buffer\",\"data\":[208,191,173,14,213,84,179,162,253,151,120,66,97,51,90,155,55,239,145,154,52,16,197,112,238,25,227,189,59,156,73,31,185,0,56,90,180,228,157,3,19,165,153,180,36,163,133,194,88,3,142,63,84,36,29,107,156,223,14,115,136,160,216,118,95,178,33,53,153,153,39,17,65,34,1,0,0,0,0,0,0,0,0,0,0,0,0,0,0,1,0,0,0,0,0,0,0,0,0,0,0,0,0,0,0,0,0,0,0,0,0,0,0,0,0,0,0,0,0,0,0,0,0,0,0,0,0,0,0,0,0,0,0,0,0,0,0,0,0,0,0,0,0,0,0,0,0,0,0,0,0,0,0,0,0,0,0,0,0,0,0,0,0,0,0,0,0,0]}",
      "executable": false,
      "lamports": 2060160,
      "owner": "crcBwD7wUjzwsy8tJsVCzZvBTHeq5GoboGg84YraRyd",
      "rentEpoch": 0,
      "type": "rewardEntry",
      "parsed": {
        "bump": "253",
        "stakeEntry": "BCGvNs9Mfn4ub1kadwpAVaJ4CWJi8whQWB1MpEaRgXXQ",
        "rewardDistributor": "C9SCyVUfoNJnYQDWgWN8CHQErjo7oNeRZk4kePJR7Cak",
        "rewardSecondsReceived": "290",
        "multiplier": "1"
      }
    },
    {
      "pubkey": "GmZ1uB41QS4qPwquvCeKKPF3daPRWcqbVtL7A17L72Ty",
      "data": "{\"type\":\"Buffer\",\"data\":[208,191,173,14,213,84,179,162,255,235,40,136,79,93,67,129,244,47,146,19,45,81,173,135,221,157,181,192,22,127,122,185,137,29,216,207,9,15,106,206,253,165,153,180,36,163,133,194,88,3,142,63,84,36,29,107,156,223,14,115,136,160,216,118,95,178,33,53,153,153,39,17,65,0,0,0,0,0,0,0,0,0,0,0,0,0,0,0,0,1,0,0,0,0,0,0,0,0,0,0,0,0,0,0,0,0,0,0,0,0,0,0,0,0,0,0,0,0,0,0,0,0,0,0,0,0,0,0,0,0,0,0,0,0,0,0,0,0,0,0,0,0,0,0,0,0,0,0,0,0,0,0,0,0,0,0,0,0,0,0,0,0,0,0,0,0,0,0]}",
      "executable": false,
      "lamports": 2060160,
      "owner": "crcBwD7wUjzwsy8tJsVCzZvBTHeq5GoboGg84YraRyd",
      "rentEpoch": 0,
      "type": "rewardEntry",
      "parsed": {
        "bump": "255",
        "stakeEntry": "Gpxf45crqeu2fGTYTfHR2PkAvUYEcTqzUGxeufdS1Q6G",
        "rewardDistributor": "C9SCyVUfoNJnYQDWgWN8CHQErjo7oNeRZk4kePJR7Cak",
        "rewardSecondsReceived": "0",
        "multiplier": "1"
      }
    },
    {
      "pubkey": "2kd5MRKRAFsmp3kS6GbUR2PvKfLebPUD53iJVS2yvCEN",
      "data": "{\"type\":\"Buffer\",\"data\":[208,191,173,14,213,84,179,162,250,187,57,211,125,154,62,137,197,183,58,230,100,11,82,95,173,124,107,50,70,107,145,166,155,20,0,63,71,36,136,213,206,165,153,180,36,163,133,194,88,3,142,63,84,36,29,107,156,223,14,115,136,160,216,118,95,178,33,53,153,153,39,17,65,0,0,0,0,0,0,0,0,0,0,0,0,0,0,0,0,1,0,0,0,0,0,0,0,0,0,0,0,0,0,0,0,0,0,0,0,0,0,0,0,0,0,0,0,0,0,0,0,0,0,0,0,0,0,0,0,0,0,0,0,0,0,0,0,0,0,0,0,0,0,0,0,0,0,0,0,0,0,0,0,0,0,0,0,0,0,0,0,0,0,0,0,0,0,0]}",
      "executable": false,
      "lamports": 2060160,
      "owner": "crcBwD7wUjzwsy8tJsVCzZvBTHeq5GoboGg84YraRyd",
      "rentEpoch": 0,
      "type": "rewardEntry",
      "parsed": {
        "bump": "250",
        "stakeEntry": "DbrP7PN1tCTvke1tkrmMfK1niqa5SosrPb9FzbvDn9ty",
        "rewardDistributor": "C9SCyVUfoNJnYQDWgWN8CHQErjo7oNeRZk4kePJR7Cak",
        "rewardSecondsReceived": "0",
        "multiplier": "1"
      }
    },
    {
      "pubkey": "EwMYVjs7x1sSr1dx4XuzJcWa591VbWVcCqqAkrB8C3VD",
      "data": "{\"type\":\"Buffer\",\"data\":[208,191,173,14,213,84,179,162,255,202,30,230,47,249,160,138,97,57,102,174,128,132,89,181,81,175,69,106,68,128,148,151,128,120,111,225,250,61,79,114,244,165,153,180,36,163,133,194,88,3,142,63,84,36,29,107,156,223,14,115,136,160,216,118,95,178,33,53,153,153,39,17,65,0,0,0,0,0,0,0,0,0,0,0,0,0,0,0,0,1,0,0,0,0,0,0,0,0,0,0,0,0,0,0,0,0,0,0,0,0,0,0,0,0,0,0,0,0,0,0,0,0,0,0,0,0,0,0,0,0,0,0,0,0,0,0,0,0,0,0,0,0,0,0,0,0,0,0,0,0,0,0,0,0,0,0,0,0,0,0,0,0,0,0,0,0,0,0]}",
      "executable": false,
      "lamports": 2060160,
      "owner": "crcBwD7wUjzwsy8tJsVCzZvBTHeq5GoboGg84YraRyd",
      "rentEpoch": 0,
      "type": "rewardEntry",
      "parsed": {
        "bump": "255",
        "stakeEntry": "EbzgaMmCoNRV2brmvsBmqJbGHeHjTz9JGhKKinb4oifu",
        "rewardDistributor": "C9SCyVUfoNJnYQDWgWN8CHQErjo7oNeRZk4kePJR7Cak",
        "rewardSecondsReceived": "0",
        "multiplier": "1"
      }
    },
    {
      "pubkey": "EdHYnzHBew5qCktFb5HLSrrV5x9DpcCcagym4KdDhrRZ",
      "data": "{\"type\":\"Buffer\",\"data\":[208,191,173,14,213,84,179,162,255,6,55,24,82,36,57,131,199,39,244,75,228,243,234,224,54,120,49,25,37,37,243,35,79,78,165,126,42,91,228,38,152,165,153,180,36,163,133,194,88,3,142,63,84,36,29,107,156,223,14,115,136,160,216,118,95,178,33,53,153,153,39,17,65,156,179,55,0,0,0,0,0,0,0,0,0,0,0,0,0,1,0,0,0,0,0,0,0,0,0,0,0,0,0,0,0,0,0,0,0,0,0,0,0,0,0,0,0,0,0,0,0,0,0,0,0,0,0,0,0,0,0,0,0,0,0,0,0,0,0,0,0,0,0,0,0,0,0,0,0,0,0,0,0,0,0,0,0,0,0,0,0,0,0,0,0,0,0,0]}",
      "executable": false,
      "lamports": 2060160,
      "owner": "crcBwD7wUjzwsy8tJsVCzZvBTHeq5GoboGg84YraRyd",
      "rentEpoch": 0,
      "type": "rewardEntry",
      "parsed": {
        "bump": "255",
        "stakeEntry": "RGB1FFo79itnnkVZXWfNt8qR71A7JtsoRDN9eYbo3V9",
        "rewardDistributor": "C9SCyVUfoNJnYQDWgWN8CHQErjo7oNeRZk4kePJR7Cak",
        "rewardSecondsReceived": "3650460",
        "multiplier": "1"
      }
    },
    {
      "pubkey": "GZuyNyLCsdosvTRxSaEEBTapfppUFFbehHGA9Sv8kSUQ",
      "data": "{\"type\":\"Buffer\",\"data\":[208,191,173,14,213,84,179,162,255,250,170,121,182,209,155,30,182,52,213,193,159,33,41,31,191,144,245,65,93,135,204,152,6,49,134,43,229,197,110,245,222,165,153,180,36,163,133,194,88,3,142,63,84,36,29,107,156,223,14,115,136,160,216,118,95,178,33,53,153,153,39,17,65,0,0,0,0,0,0,0,0,0,0,0,0,0,0,0,0,1,0,0,0,0,0,0,0,0,0,0,0,0,0,0,0,0,0,0,0,0,0,0,0,0,0,0,0,0,0,0,0,0,0,0,0,0,0,0,0,0,0,0,0,0,0,0,0,0,0,0,0,0,0,0,0,0,0,0,0,0,0,0,0,0,0,0,0,0,0,0,0,0,0,0,0,0,0,0]}",
      "executable": false,
      "lamports": 2060160,
      "owner": "crcBwD7wUjzwsy8tJsVCzZvBTHeq5GoboGg84YraRyd",
      "rentEpoch": 0,
      "type": "rewardEntry",
      "parsed": {
        "bump": "255",
        "stakeEntry": "HsVhEuXQtcSsrbCvBkU11JU74oFF4PpFQNxqUYCqjdAM",
        "rewardDistributor": "C9SCyVUfoNJnYQDWgWN8CHQErjo7oNeRZk4kePJR7Cak",
        "rewardSecondsReceived": "0",
        "multiplier": "1"
      }
    },
    {
      "pubkey": "5NcDU2U9kWLNtoTTdSbugBCLZajuyKno6scBJ2qoqW3M",
      "data": "{\"type\":\"Buffer\",\"data\":[208,191,173,14,213,84,179,162,254,171,221,38,192,223,25,126,16,224,237,200,157,166,246,173,185,190,72,144,170,175,24,250,43,90,69,244,225,130,255,243,73,165,153,180,36,163,133,194,88,3,142,63,84,36,29,107,156,223,14,115,136,160,216,118,95,178,33,53,153,153,39,17,65,244,124,42,0,0,0,0,0,0,0,0,0,0,0,0,0,1,0,0,0,0,0,0,0,0,0,0,0,0,0,0,0,0,0,0,0,0,0,0,0,0,0,0,0,0,0,0,0,0,0,0,0,0,0,0,0,0,0,0,0,0,0,0,0,0,0,0,0,0,0,0,0,0,0,0,0,0,0,0,0,0,0,0,0,0,0,0,0,0,0,0,0,0,0,0]}",
      "executable": false,
      "lamports": 2060160,
      "owner": "crcBwD7wUjzwsy8tJsVCzZvBTHeq5GoboGg84YraRyd",
      "rentEpoch": 0,
      "type": "rewardEntry",
      "parsed": {
        "bump": "254",
        "stakeEntry": "CZtJciFq51pqqfKUiQuMGPqdg1qXB5ssEScADnbA89Jg",
        "rewardDistributor": "C9SCyVUfoNJnYQDWgWN8CHQErjo7oNeRZk4kePJR7Cak",
        "rewardSecondsReceived": "2784500",
        "multiplier": "1"
      }
    },
    {
      "pubkey": "CdzowpMRTfwdPbjUgv1MX7T64W9BQwYwDRM9D368ksq5",
      "data": "{\"type\":\"Buffer\",\"data\":[208,191,173,14,213,84,179,162,255,128,86,2,171,24,10,204,145,146,31,197,15,164,132,208,15,26,67,39,212,212,155,180,160,63,143,172,31,138,170,186,66,165,153,180,36,163,133,194,88,3,142,63,84,36,29,107,156,223,14,115,136,160,216,118,95,178,33,53,153,153,39,17,65,120,0,0,0,0,0,0,0,0,0,0,0,0,0,0,0,1,0,0,0,0,0,0,0,0,0,0,0,0,0,0,0,0,0,0,0,0,0,0,0,0,0,0,0,0,0,0,0,0,0,0,0,0,0,0,0,0,0,0,0,0,0,0,0,0,0,0,0,0,0,0,0,0,0,0,0,0,0,0,0,0,0,0,0,0,0,0,0,0,0,0,0,0,0,0]}",
      "executable": false,
      "lamports": 2060160,
      "owner": "crcBwD7wUjzwsy8tJsVCzZvBTHeq5GoboGg84YraRyd",
      "rentEpoch": 0,
      "type": "rewardEntry",
      "parsed": {
        "bump": "255",
        "stakeEntry": "9dyFhL5r4NEmmvVfrYMGsHHzFV2RGAYQJzpr5wPWEiVF",
        "rewardDistributor": "C9SCyVUfoNJnYQDWgWN8CHQErjo7oNeRZk4kePJR7Cak",
        "rewardSecondsReceived": "120",
        "multiplier": "1"
      }
    },
    {
      "pubkey": "54c5CBDwusE8dqEtdstkNQAJsUjvG4QHF9TPugEqYFM5",
      "data": "{\"type\":\"Buffer\",\"data\":[208,191,173,14,213,84,179,162,255,94,156,175,235,223,188,214,0,106,158,22,144,176,193,30,50,179,80,78,62,123,220,92,60,168,95,169,233,107,141,115,238,165,153,180,36,163,133,194,88,3,142,63,84,36,29,107,156,223,14,115,136,160,216,118,95,178,33,53,153,153,39,17,65,212,118,30,0,0,0,0,0,0,0,0,0,0,0,0,0,1,0,0,0,0,0,0,0,0,0,0,0,0,0,0,0,0,0,0,0,0,0,0,0,0,0,0,0,0,0,0,0,0,0,0,0,0,0,0,0,0,0,0,0,0,0,0,0,0,0,0,0,0,0,0,0,0,0,0,0,0,0,0,0,0,0,0,0,0,0,0,0,0,0,0,0,0,0,0]}",
      "executable": false,
      "lamports": 2060160,
      "owner": "crcBwD7wUjzwsy8tJsVCzZvBTHeq5GoboGg84YraRyd",
      "rentEpoch": 0,
      "type": "rewardEntry",
      "parsed": {
        "bump": "255",
        "stakeEntry": "7NKu7gQNtxxyGrpNWx75QzzqYZA3xGtNu6XwVB33NfsT",
        "rewardDistributor": "C9SCyVUfoNJnYQDWgWN8CHQErjo7oNeRZk4kePJR7Cak",
        "rewardSecondsReceived": "1996500",
        "multiplier": "1"
      }
    }
  ]
}